nw/__init__.py
nw-0.0.5.dist-info/licenses/LICENSE
nw-0.0.5.dist-info/METADATA
nw-0.0.5.dist-info/WHEEL
nw-0.0.5.dist-info/top_level.txt
nw-0.0.5.dist-info/RECORD
