Metadata-Version: 2.4
Name: nw
Version: 0.0.5
Summary: Association mining
Home-page: https://github.com/t-c-w/nw
Author: Thor Whalen
License: apache-2.0
Platform: any
License-File: LICENSE
Dynamic: license-file
